<?xml version="1.0" encoding="utf-8"?>
<search>
  
  
  
  <entry>
    <title>展映预告: 瑞士 FANTOCHE 国际动画电影节</title>
    <link href="/2022/08/29/%E5%B1%95%E6%98%A0%E9%A2%84%E5%91%8A-%E7%91%9E%E5%A3%AB-FANTOCHE-%E5%9B%BD%E9%99%85%E5%8A%A8%E7%94%BB%E7%94%B5%E5%BD%B1%E8%8A%82/"/>
    <url>/2022/08/29/%E5%B1%95%E6%98%A0%E9%A2%84%E5%91%8A-%E7%91%9E%E5%A3%AB-FANTOCHE-%E5%9B%BD%E9%99%85%E5%8A%A8%E7%94%BB%E7%94%B5%E5%BD%B1%E8%8A%82/</url>
    
    <content type="html"><![CDATA[<h1 id="FANTOCHE-展映影片信息表"><a href="#FANTOCHE-展映影片信息表" class="headerlink" title="FANTOCHE 展映影片信息表"></a>FANTOCHE 展映影片信息表</h1><p><img src="http://img.heqing.co/20220829101858.png" alt="展映信息"></p>]]></content>
    
    
    <categories>
      
      <category>动画周</category>
      
    </categories>
    
    
    <tags>
      
      <tag>动画周</tag>
      
    </tags>
    
  </entry>
  
  
  
  <entry>
    <title>倒计时 2 周！2022 第四届东布洲国际动画周竞赛单元作品征集</title>
    <link href="/2022/08/17/%E5%80%92%E8%AE%A1%E6%97%B6-2-%E5%91%A8%EF%BC%812022-%E7%AC%AC%E5%9B%9B%E5%B1%8A%E4%B8%9C%E5%B8%83%E6%B4%B2%E5%9B%BD%E9%99%85%E5%8A%A8%E7%94%BB%E5%91%A8%E7%AB%9E%E8%B5%9B%E5%8D%95%E5%85%83%E4%BD%9C%E5%93%81%E5%BE%81%E9%9B%86/"/>
    <url>/2022/08/17/%E5%80%92%E8%AE%A1%E6%97%B6-2-%E5%91%A8%EF%BC%812022-%E7%AC%AC%E5%9B%9B%E5%B1%8A%E4%B8%9C%E5%B8%83%E6%B4%B2%E5%9B%BD%E9%99%85%E5%8A%A8%E7%94%BB%E5%91%A8%E7%AB%9E%E8%B5%9B%E5%8D%95%E5%85%83%E4%BD%9C%E5%93%81%E5%BE%81%E9%9B%86/</url>
    
    <content type="html"><![CDATA[<p>第四届 “东布洲国际动画周” 暨第十一届 “中国独立动画电影论坛” 将于 2022 年 10 月下旬在江苏海门临江新区举办。</p><p>竞赛单元作品征集截止日期为 <strong>2022 年 8 月 31 日</strong>。</p><p>目前<strong>仅剩 2 周</strong>的时间！</p><p>欢迎大家积极参加报名投递作品。</p><p>具体报名方式及规则如下：</p><h2 id="作品征集时间"><a href="#作品征集时间" class="headerlink" title="作品征集时间"></a>作品征集时间</h2><p>2022 年 6 月 1 日 - 2022 年 8 月 31 日</p><h2 id="奖项设置"><a href="#奖项设置" class="headerlink" title="奖项设置"></a>奖项设置</h2><p>论坛大奖、论坛特别奖<br>实验动画奖<br>今敏奖<br>学生作品奖、评委特别推荐奖</p><h2 id="作品征集细则"><a href="#作品征集细则" class="headerlink" title="作品征集细则"></a>作品征集细则</h2><ul><li>不收取任何报名费用。</li><li>参赛作品需为逐帧动画，包括电脑绘图动画。</li><li>作品内容题材不限。</li><li>作品应完成于 2021 年 7 月之后。不接受过去曾参加过本竞赛的作品再次参赛。 </li><li>未获得版权许可的内容，剧本，音乐等不可用于所提交的作品。如无法获得许可，将失去参赛资格。有第三者发起侵权、索赔等诉讼时，东布洲国际动画周概不负责。</li><li>其他电影节已获奖作品仍然可以参赛，但需在报名表上列出所获奖项信息。</li><li>只要达到上述条件，同一参赛者可提交多部作品参赛。</li></ul><h2 id="作品投递所需资料"><a href="#作品投递所需资料" class="headerlink" title="作品投递所需资料"></a>作品投递所需资料</h2><h3 id="【报名表】"><a href="#【报名表】" class="headerlink" title="【报名表】"></a>【报名表】</h3><p>请参赛者通过官方渠道下载：请关注官方微信公众号，回复 “报名” 即可下载报名表。</p><h3 id="【导演简历、照片】"><a href="#【导演简历、照片】" class="headerlink" title="【导演简历、照片】"></a>【导演简历、照片】</h3><ul><li>简历格式可参见报名表 “附表 1”。</li><li>清晰的导演 &#x2F; 团队成员的生活照（5M 左右，JPEG&#x2F;PNG，300dpi）</li></ul><h3 id="【作品图片】"><a href="#【作品图片】" class="headerlink" title="【作品图片】"></a>【作品图片】</h3><ul><li>1 张海报、3 张作品剧照（5M 左右，JPEG&#x2F;PNG，300dpi）</li><li>照片文件需以人名或作品名命名。</li><li>这些照片与图片将被刊登于论坛官方平台、宣传单等广告物料或宣传册中。组委会可能会将收到的照片与图片剪辑使用，敬请谅解。</li></ul><h3 id="【影片】"><a href="#【影片】" class="headerlink" title="【影片】"></a>【影片】</h3><ul><li>影片格式可采用：MOV、AVI、MP4、或 WMV 。作品分辨率不得小于 720p ，并尽量采用低压缩或无损压缩方式。暂不接受 DCP 文件。</li><li>如果你的作品入围，需要在 10 月 10 日前向论坛组委会提供用于展映的高清格式：MOV、MPEG、MWV、MP4（H.264，分辨率为 1920 × 1080 及以上），暂不接受 DCP、35mm、16mm 胶片、HD-CAM 等格式。</li><li>有旁白或对白的影片请添加英文字幕。中文影片请添加中英文双语字幕。</li></ul><h2 id="作品投递方式"><a href="#作品投递方式" class="headerlink" title="作品投递方式"></a>作品投递方式</h2><h3 id="【-Email-投递】"><a href="#【-Email-投递】" class="headerlink" title="【 Email 投递】"></a>【 Email 投递】</h3><ul><li>一份报名表仅代表一部作品，请将【报名表】、【导演简历、照片】、【作品图片】和【影片】一起邮件提交至组委会指定邮箱。</li><li>报名邮件请以 “2022 第四届东布洲国际动画周竞赛单元 + 作品名 + 作者姓名” 为邮件主题。网盘地址下载、电子邮件超大附件皆可。</li><li>邮箱地址：<a href="mailto:&#115;&#x75;&#98;&#x6d;&#105;&#115;&#115;&#105;&#111;&#110;&#115;&#x40;&#116;&#111;&#112;&#x75;&#x69;&#97;&#119;&#46;&#99;&#111;&#109;">&#115;&#x75;&#98;&#x6d;&#105;&#115;&#115;&#105;&#111;&#110;&#115;&#x40;&#116;&#111;&#112;&#x75;&#x69;&#97;&#119;&#46;&#99;&#111;&#109;</a></li></ul><h3 id="【-Film-Freeway-在线投递】"><a href="#【-Film-Freeway-在线投递】" class="headerlink" title="【 Film Freeway 在线投递】"></a>【 Film Freeway 在线投递】</h3><p> <a href="https://filmfreeway.com/TOPUInternationalAnimationWeek">https://filmfreeway.com/TOPUInternationalAnimationWeek</a></p><h3 id="【邮寄快件】"><a href="#【邮寄快件】" class="headerlink" title="【邮寄快件】"></a>【邮寄快件】</h3><p>一份报名表仅代表一部作品，【报名表】、【导演简历、照片】、【作品图片】和【影片】一起刻盘邮寄至组委会指定地址。</p><ol><li>请在光盘上标注作者姓名、作品名称、联系电话。</li><li>请在快件上标注 “2022 第四届东布洲国际动画周竞赛单元”。</li><li>所有作品都有丢失的可能，论坛有权拒收任何到付邮费的邮件快递。</li><li>因报名所产生的邮费等所有费用均由参赛者承担。</li><li>邮寄作品按照当地邮戳时间为准。请在规定时间内投递，逾期将失去参加资格。</li></ol><h2 id="联系方式"><a href="#联系方式" class="headerlink" title="联系方式"></a>联系方式</h2><p>邮寄地址：江苏省南通市海门临江新区洞庭湖路 99 号东布洲国际动画孵化创作基地<br>收件人：东布洲国际动画周组委会<br>邮编：226100<br>联系电话：0086 138 1030 2830 或 0086 176 1083 2391</p><h2 id="报名表"><a href="#报名表" class="headerlink" title="报名表"></a>报名表</h2><p>请点击下载<a href="https://pan.baidu.com/share/init?surl=HNfhBOqIVXrpdAMEln18lw">报名表</a>，提取码 “ 7m2i ”</p>]]></content>
    
    
    <categories>
      
      <category>动画周</category>
      
    </categories>
    
    
    <tags>
      
      <tag>征集</tag>
      
    </tags>
    
  </entry>
  
  
  
  <entry>
    <title>欢迎来到现实！——第四届东布洲国际动画周主题发布</title>
    <link href="/2022/08/11/%E6%AC%A2%E8%BF%8E%E6%9D%A5%E5%88%B0%E7%8E%B0%E5%AE%9E%EF%BC%81%E2%80%94%E2%80%94%E7%AC%AC%E5%9B%9B%E5%B1%8A%E4%B8%9C%E5%B8%83%E6%B4%B2%E5%9B%BD%E9%99%85%E5%8A%A8%E7%94%BB%E5%91%A8%E4%B8%BB%E9%A2%98%E5%8F%91%E5%B8%83/"/>
    <url>/2022/08/11/%E6%AC%A2%E8%BF%8E%E6%9D%A5%E5%88%B0%E7%8E%B0%E5%AE%9E%EF%BC%81%E2%80%94%E2%80%94%E7%AC%AC%E5%9B%9B%E5%B1%8A%E4%B8%9C%E5%B8%83%E6%B4%B2%E5%9B%BD%E9%99%85%E5%8A%A8%E7%94%BB%E5%91%A8%E4%B8%BB%E9%A2%98%E5%8F%91%E5%B8%83/</url>
    
    <content type="html"><![CDATA[<p>第四届 “东布洲国际动画周” 暨第十一届 “中国独立动画电影论坛”，将于 2022 年 10 月下旬在江苏省南通市海门区临江新区正式举行。  </p><p>本届东布洲国际动画周（TOPUIAW）由北京电影学院动画学院副教授陈廖宇、追光动画联合创始人于洲、中国独立动画电影论坛创始人皮三担任策展人。</p><p>本次活动主题为 <strong>“欢迎来到现实！”</strong></p><p>对于主题，每位策展人有着不同的理解。</p><h2 id="陈廖宇"><a href="#陈廖宇" class="headerlink" title="陈廖宇"></a>陈廖宇</h2><center><img src="http://img.heqing.co/20220811155659.png" width="35%" height="35%" /></center><br/><blockquote><p>我们生活在现实中。<br>我们生活在现实中？<br>我们以为自己生活在现实中。</p></blockquote><blockquote><p>我们在现实之上架设了层层叠叠的词语，<br>制造了一个我们以为的现实。</p></blockquote><blockquote><p>不知从何时开始，<br>我们坐上告别现实的列车，<br>一路狂奔离现实越来越远。</p></blockquote><blockquote><p>而动画总是被当作驶离现实的天然列车，<br>我们夸她天马行空，<br>我们夸她无所不能，<br>但是如果穿过所有的想象力，<br>最终不是驶向现实，<br>那么她的意义又是什么呢？<br>难道仅仅是为了帮我们离开现实吗？</p></blockquote><blockquote><p>第四届东布洲国际动画周，<br>就是动画列车驶向现实的一站。<br>在这一站，<br>我们关心动画和现实。<br>对于因为疫情已经习惯了非现实交流的各位，<br>更要说一声：<br>欢迎来到现实！</p></blockquote><h2 id="于洲"><a href="#于洲" class="headerlink" title="于洲"></a>于洲</h2><center><img src="http://img.heqing.co/于洲.png" width="35%" height="35%" /></center><br/><blockquote><p>三年前的时候，没有人能想到 2022 年的世界会是这个样子：5 亿多人确诊新冠，近 630 万人被夺去生命。如果这是一部电影，那它的类型可能是奇幻、灾难，甚至荒诞。而这，正是当下的现实。</p></blockquote><blockquote><p>经历这样的困扰和不幸，认清了我们生存的世界依然热爱生活，依然怀抱梦想，保持善意和好奇，这是否还是我们对现实的态度？</p></blockquote><blockquote><p>欢迎来到现实！</p></blockquote><blockquote><p>现实的世界是多元的，不是两极的；<br>现实的世界是万变的，不是静止的；<br>现实的世界是感知的，不是推送的；<br>现实的世界是体验的，不是臆想的。</p></blockquote><blockquote><p>我们的身体在感知、体验这个多元、万变的世界，而我们的心可以飞翔；动画是我们从心里长出的翅膀，带我们去到想去的地方。</p></blockquote><blockquote><p>期待今年的东布洲是一个绿洲，一个现实的绿洲。</p></blockquote><h2 id="皮三"><a href="#皮三" class="headerlink" title="皮三"></a>皮三</h2><center><img src="http://img.heqing.co/20220811155904.png" width="35%" height="35%" /></center><br/><blockquote><p>今年戛纳电影节的海报，是电影《楚门的世界》的剧照，犹如玛格利特超现实主义绘画风格：蓝天白云的巨幕前，男主角走上楼梯，那是楚门想要走出“虚拟”世界，试图打开“现实”世界大门的最后一瞬间。</p></blockquote><blockquote><p>这或许是近几年全世界多数人的感受，突如其来的疾病、战争、经济危机……以及这一年来，我们身处巨大荒谬现场的无助，我们不知道自己身处何方，需要找到生存的逻辑和提问的勇气。这一切都迫使我们开始重新思考，何为虚幻？何为现实？<br>在此情境下，欢迎来到现实！</p></blockquote><blockquote><p>作为动画从业者，经历了前几年文化娱乐行业的短暂繁荣，行业开始呈现一些困顿与停滞。作为最习惯在恶劣环境生存的国人，我们还有能力和条件热爱动画么？或者说，我们不得不思考，如何通过工作再次热爱生活，也找到现实存在的意义。<br>在此情景下，欢迎来到现实！</p></blockquote><blockquote><p>动画创作本身，也需要梳理，经历了各种神话与玄幻的题材和视觉轰炸，各种抽象和技术的语言实验，我们一次次的给动画贴上刻板印象的标签，动画和现实世界的关联究竟如何？动画题材的现实性意义何在？如何看待动画作品精神的现实性和题材的现实性？<br>在此情景下，欢迎来到现实！</p></blockquote><blockquote><p>哲学家曾把人类的精神分为真实界，幻想界和隐喻界，动画作为认识世界和创造的一种方式，也是时候需要像楚门一样去怀疑当下的世界，从而找到更广阔的可能性。<br>欢迎来到现实！</p></blockquote>]]></content>
    
    
    <categories>
      
      <category>动画周</category>
      
    </categories>
    
    
    <tags>
      
      <tag>动画周</tag>
      
    </tags>
    
  </entry>
  
  
  
  <entry>
    <title>东布洲孵化项目 — 王家琪《崔文子学仙》入围 Encounters Film Festival</title>
    <link href="/2022/08/04/%E5%AD%B5%E5%8C%96%E9%A1%B9%E7%9B%AE%E8%BF%9B%E5%B1%95%E5%88%86%E4%BA%AB-%E2%80%94%E2%80%94-%E3%80%8A%E5%B4%94%E6%96%87%E5%AD%90%E5%AD%A6%E4%BB%99%E3%80%8B%E5%85%A5%E5%9B%B4-Encounters-Film-Festival/"/>
    <url>/2022/08/04/%E5%AD%B5%E5%8C%96%E9%A1%B9%E7%9B%AE%E8%BF%9B%E5%B1%95%E5%88%86%E4%BA%AB-%E2%80%94%E2%80%94-%E3%80%8A%E5%B4%94%E6%96%87%E5%AD%90%E5%AD%A6%E4%BB%99%E3%80%8B%E5%85%A5%E5%9B%B4-Encounters-Film-Festival/</url>
    
    <content type="html"><![CDATA[<p><img src="http://img.heqing.co/20220721205229.png"></p><p>自 2020 年东布洲国际动画基地开启动画孵化项目以来，已有多个项目陆续完成孵化。本着助力动画创作 “最初一公里” 的初衷，我们不仅支持商业动画的创作与孵化，同时也更加关注原创独立动画的发展，寄希望于中国的独立动画创作能走的更远。</p><p>本次介绍的 <strong>《崔文子学仙》</strong> 是 2021 年入驻基地的独立动画项目，动画以志怪小说《搜神记》里的一则故事为原型，探讨了人与自然能量场之间的关系。截止到目前的投递情况，《崔文子学仙》已经入围 <strong>英国 Encounters Film Festival</strong> 与 <strong>瑞士萨维尼动画电影节</strong>。</p><p>《崔文子学仙》将于 2022 年 10 月 1 日（星期六）上午 10:00 ，作为 <strong>Encounters Film Festival “Children’s Jury” 单元</strong> 的组成部分，在英国布里斯托的 Watershed 线下放映，同时其官方组委会也将通过 Eventive 在线放映。</p><p><img src="http://img.heqing.co/20220804154206.png"></p><p>Encounters Film Festival 是国际领先的短片、动画和沉浸式动态影像作品的国际竞赛之一，致力于发现、支持和发展新的电影制作人才，将行业和观众联系在一起，庆祝短片的创造力、多样性和影响力。自 2010 年后，作为欧洲 15 个知名电影节其中之一，成为奥斯卡金像奖、英国电影学院奖和欧洲电影奖的官方门户。</p><p><img src="http://img.heqing.co/20220721205307.png"></p><blockquote><p>“曾经有一只美丽的生物，在我梦里出现过。但是之后我再也没有见到过它。” </p></blockquote><p>自然界中，能量不但可以从一个物体转移到另一个物体，多种能量之间还可以相互转化；这种特殊的循环就会产生能量场。物与物之间的转化是某种不变的能量的体现。自然能量以大鸟的姿态示人又离去，给人留下似梦非梦的物哀之情。</p><h1 id="创作人介绍"><a href="#创作人介绍" class="headerlink" title="创作人介绍"></a>创作人介绍</h1><p><strong>王家琪</strong><br>本科毕业于中央美术学院，研究生毕业于英国皇家艺术学院。她的动画作品善于通过符号隐喻的方式讲述真实的故事，通过版刻的媒介将粗糙的画面质感与细腻的独白结合。《2.3 x 2.6 x 3.2》曾参加伦敦国际动画节、渥太华国际动画节和爱丁堡国际电影节，还赢得了 Monstra 国际动画节的最佳学生影片。《龙头树》获得第三届东布洲国际动画周 “实验动画奖”。<br>网站: <a href="http://www.jackiestudio.com/">www.jackiestudio.com</a><br>邮箱：<a href="mailto:&#106;&#97;&#99;&#107;&#105;&#x65;&#x77;&#x6f;&#x72;&#107;&#64;&#111;&#x75;&#116;&#x6c;&#111;&#111;&#107;&#46;&#99;&#111;&#x6d;">&#106;&#97;&#99;&#107;&#105;&#x65;&#x77;&#x6f;&#x72;&#107;&#64;&#111;&#x75;&#116;&#x6c;&#111;&#111;&#107;&#46;&#99;&#111;&#x6d;</a></p><p><img src="http://img.heqing.co/20220721205514.png"><br>《崔文子学仙》的国画风背景，由岳一川绘制。岳一川本科和硕士均毕业于中央美术学院，其作品入选联合国非物质文化遗产、美国集邮集团、欧洲集邮集团联合出品 “庆祝建国 70 周年主题邮票” 出版并发行。目前于首都师范大学美术学院攻读博士学位。</p><p><img src="http://img.heqing.co/20220721205553.png"></p><h1 id="角色设计"><a href="#角色设计" class="headerlink" title="角色设计"></a>角色设计</h1><p><img src="http://img.heqing.co/20220721205728.png"><br><img src="http://img.heqing.co/20220721205739.png"><br><img src="http://img.heqing.co/20220721205752.png"></p><h1 id="影片截图"><a href="#影片截图" class="headerlink" title="影片截图"></a>影片截图</h1><p><img src="http://img.heqing.co/20220721205814.png"><br><img src="http://img.heqing.co/20220721205822.png"><br><img src="http://img.heqing.co/20220721205833.png"><br><img src="http://img.heqing.co/20220721205846.png"></p>]]></content>
    
    
    <categories>
      
      <category>孵化</category>
      
    </categories>
    
    
    <tags>
      
      <tag>孵化分享</tag>
      
    </tags>
    
  </entry>
  
  
  
  <entry>
    <title>倒计时 1 个月！2022 第四届东布洲国际动画周竞赛单元作品征集</title>
    <link href="/2022/08/01/%E5%80%92%E8%AE%A1%E6%97%B6-1-%E4%B8%AA%E6%9C%88%EF%BC%812022-%E7%AC%AC%E5%9B%9B%E5%B1%8A%E4%B8%9C%E5%B8%83%E6%B4%B2%E5%9B%BD%E9%99%85%E5%8A%A8%E7%94%BB%E5%91%A8%E7%AB%9E%E8%B5%9B%E5%8D%95%E5%85%83%E4%BD%9C%E5%93%81%E5%BE%81%E9%9B%86/"/>
    <url>/2022/08/01/%E5%80%92%E8%AE%A1%E6%97%B6-1-%E4%B8%AA%E6%9C%88%EF%BC%812022-%E7%AC%AC%E5%9B%9B%E5%B1%8A%E4%B8%9C%E5%B8%83%E6%B4%B2%E5%9B%BD%E9%99%85%E5%8A%A8%E7%94%BB%E5%91%A8%E7%AB%9E%E8%B5%9B%E5%8D%95%E5%85%83%E4%BD%9C%E5%93%81%E5%BE%81%E9%9B%86/</url>
    
    <content type="html"><![CDATA[<p>第四届 “东布洲国际动画周” 暨第十一届 “中国独立动画电影论坛” 将于 2022 年 10 月下旬在江苏海门临江新区举办。</p><p>竞赛单元作品征集截止日期为 <strong>2022 年 8 月 31 日</strong>。</p><p>目前<strong>仅剩 1 个月</strong>的时间！</p><p>欢迎大家积极参加报名投递作品。</p><p>具体报名方式及规则如下：</p><h2 id="作品征集时间"><a href="#作品征集时间" class="headerlink" title="作品征集时间"></a>作品征集时间</h2><p>2022 年 6 月 1 日 - 2022 年 8 月 31 日</p><h2 id="奖项设置"><a href="#奖项设置" class="headerlink" title="奖项设置"></a>奖项设置</h2><p>论坛大奖、论坛特别奖<br>实验动画奖<br>今敏奖<br>学生作品奖、评委特别推荐奖</p><h2 id="作品征集细则"><a href="#作品征集细则" class="headerlink" title="作品征集细则"></a>作品征集细则</h2><ul><li>不收取任何报名费用。</li><li>参赛作品需为逐帧动画，包括电脑绘图动画。</li><li>作品内容题材不限。</li><li>作品应完成于 2021 年 7 月之后。不接受过去曾参加过本竞赛的作品再次参赛。 </li><li>未获得版权许可的内容，剧本，音乐等不可用于所提交的作品。如无法获得许可，将失去参赛资格。有第三者发起侵权、索赔等诉讼时，东布洲国际动画周概不负责。</li><li>其他电影节已获奖作品仍然可以参赛，但需在报名表上列出所获奖项信息。</li><li>只要达到上述条件，同一参赛者可提交多部作品参赛。</li></ul><h2 id="作品投递所需资料"><a href="#作品投递所需资料" class="headerlink" title="作品投递所需资料"></a>作品投递所需资料</h2><h3 id="【报名表】"><a href="#【报名表】" class="headerlink" title="【报名表】"></a>【报名表】</h3><p>请参赛者通过官方渠道下载：请关注官方微信公众号，回复 “报名” 即可下载报名表。</p><h3 id="【导演简历、照片】"><a href="#【导演简历、照片】" class="headerlink" title="【导演简历、照片】"></a>【导演简历、照片】</h3><ul><li>简历格式可参见报名表 “附表 1”。</li><li>清晰的导演 &#x2F; 团队成员的生活照（5M 左右，JPEG&#x2F;PNG，300dpi）</li></ul><h3 id="【作品图片】"><a href="#【作品图片】" class="headerlink" title="【作品图片】"></a>【作品图片】</h3><ul><li>1 张海报、3 张作品剧照（5M 左右，JPEG&#x2F;PNG，300dpi）</li><li>照片文件需以人名或作品名命名。</li><li>这些照片与图片将被刊登于论坛官方平台、宣传单等广告物料或宣传册中。组委会可能会将收到的照片与图片剪辑使用，敬请谅解。</li></ul><h3 id="【影片】"><a href="#【影片】" class="headerlink" title="【影片】"></a>【影片】</h3><ul><li>影片格式可采用：MOV、AVI、MP4、或 WMV 。作品分辨率不得小于 720p ，并尽量采用低压缩或无损压缩方式。暂不接受 DCP 文件。</li><li>如果你的作品入围，需要在 10 月 10 日前向论坛组委会提供用于展映的高清格式：MOV、MPEG、MWV、MP4（H.264，分辨率为 1920 × 1080 及以上），暂不接受 DCP、35mm、16mm 胶片、HD-CAM 等格式。</li><li>有旁白或对白的影片请添加英文字幕。中文影片请添加中英文双语字幕。</li></ul><h2 id="作品投递方式"><a href="#作品投递方式" class="headerlink" title="作品投递方式"></a>作品投递方式</h2><h3 id="【-Email-投递】"><a href="#【-Email-投递】" class="headerlink" title="【 Email 投递】"></a>【 Email 投递】</h3><ul><li>一份报名表仅代表一部作品，请将【报名表】、【导演简历、照片】、【作品图片】和【影片】一起邮件提交至组委会指定邮箱。</li><li>报名邮件请以 “2022 第四届东布洲国际动画周竞赛单元 + 作品名 + 作者姓名” 为邮件主题。网盘地址下载、电子邮件超大附件皆可。</li><li>邮箱地址：<a href="mailto:&#x73;&#x75;&#x62;&#109;&#105;&#x73;&#x73;&#x69;&#111;&#110;&#x73;&#x40;&#x74;&#x6f;&#x70;&#x75;&#105;&#x61;&#119;&#x2e;&#99;&#x6f;&#x6d;">&#x73;&#x75;&#x62;&#109;&#105;&#x73;&#x73;&#x69;&#111;&#110;&#x73;&#x40;&#x74;&#x6f;&#x70;&#x75;&#105;&#x61;&#119;&#x2e;&#99;&#x6f;&#x6d;</a></li></ul><h3 id="【-Film-Freeway-在线投递】"><a href="#【-Film-Freeway-在线投递】" class="headerlink" title="【 Film Freeway 在线投递】"></a>【 Film Freeway 在线投递】</h3><p> <a href="https://filmfreeway.com/TOPUInternationalAnimationWeek">https://filmfreeway.com/TOPUInternationalAnimationWeek</a></p><h3 id="【邮寄快件】"><a href="#【邮寄快件】" class="headerlink" title="【邮寄快件】"></a>【邮寄快件】</h3><p>一份报名表仅代表一部作品，【报名表】、【导演简历、照片】、【作品图片】和【影片】一起刻盘邮寄至组委会指定地址。</p><ol><li>请在光盘上标注作者姓名、作品名称、联系电话。</li><li>请在快件上标注 “2022 第四届东布洲国际动画周竞赛单元”。</li><li>所有作品都有丢失的可能，论坛有权拒收任何到付邮费的邮件快递。</li><li>因报名所产生的邮费等所有费用均由参赛者承担。</li><li>邮寄作品按照当地邮戳时间为准。请在规定时间内投递，逾期将失去参加资格。</li></ol><h2 id="联系方式"><a href="#联系方式" class="headerlink" title="联系方式"></a>联系方式</h2><p>邮寄地址：江苏省南通市海门临江新区洞庭湖路 99 号东布洲国际动画孵化创作基地<br>收件人：东布洲国际动画周组委会<br>邮编：226100<br>联系电话：0086 138 1030 2830 或 0086 176 1083 2391</p><h2 id="报名表"><a href="#报名表" class="headerlink" title="报名表"></a>报名表</h2><p>请点击下载<a href="https://pan.baidu.com/share/init?surl=HNfhBOqIVXrpdAMEln18lw">报名表</a>，提取码 “ 7m2i ”</p>]]></content>
    
    
    <categories>
      
      <category>动画周</category>
      
    </categories>
    
    
    <tags>
      
      <tag>征集</tag>
      
    </tags>
    
  </entry>
  
  
  
  <entry>
    <title>北京聚合影联 × 东布洲动画基地达成战略合作</title>
    <link href="/2022/07/29/%E5%8C%97%E4%BA%AC%E8%81%9A%E5%90%88%E5%BD%B1%E8%81%94-%C3%97-%E4%B8%9C%E5%B8%83%E6%B4%B2%E5%8A%A8%E7%94%BB%E5%9F%BA%E5%9C%B0%E8%BE%BE%E6%88%90%E6%88%98%E7%95%A5%E5%90%88%E4%BD%9C/"/>
    <url>/2022/07/29/%E5%8C%97%E4%BA%AC%E8%81%9A%E5%90%88%E5%BD%B1%E8%81%94-%C3%97-%E4%B8%9C%E5%B8%83%E6%B4%B2%E5%8A%A8%E7%94%BB%E5%9F%BA%E5%9C%B0%E8%BE%BE%E6%88%90%E6%88%98%E7%95%A5%E5%90%88%E4%BD%9C/</url>
    
    <content type="html"><![CDATA[<p><img src="http://img.heqing.co/20220729185820.png" alt="签约"></p><p>近日，北京聚合影联文化传媒有限公司与东布洲国际动画孵化创作基地正式达成战略合作，并以此为契机全面深化合作关系，将围绕动画 IP 开发、投资制作及营销发行等多个领域开展深度业务合作。</p><p><img src="http://img.heqing.co/20220729185920.png"></p><p>北京聚合影联文化传媒有限公司是一家集电影投资、渠道发行、营销策划、版权商务等为一体的一站式电影公司，公司秉承 “创造电影真实价值” 的核心理念，聚合行业内优秀资源，对传统电影发行模式进行大胆创新，采用 “项目制” 管理模式，为电影提供全流程的宣发方案。代表作有 <strong>《战狼 Ⅱ》《流浪地球》《我不是药神》《幕后玩家》《无问西东》 《绣春刀・修罗战场》《西游记之大圣归来》《蓝精灵 2》《百鸟朝凤》《血战钢锯岭》《心花路放》《同桌的你》《神奇马戏团》《英雄本色 4》《超凡蜘蛛侠 2》《七十七天》</strong>等。</p><p><img src="http://img.heqing.co/20220729185953.png"></p><p>东布洲国际动画孵化创作基地由南通东娱文化传媒有限公司发起，以 “<strong>助力原创动画最初一公里，孵化优质动画内容和品牌</strong>” 为核心理念，专注于打造原创优质动画内容和品牌孵化的服务平台。为了更好的帮助国内外的动画人、原创作品，甄选优秀创意、发掘优秀团队，基地将投入资源和资金，与他们共同完善作品的 “<strong>最初一公里</strong>”，也即，把一个点子或想法逐步孵化成可以进入成熟开发阶段的项目。截至目前，已有 <strong>20</strong> 个项目在基地入驻，其中 <strong>13</strong> 个孵化项目已阶段性完成孵化工作。</p><p>随着国内动画市场规模不断的扩大，观众对动画内容的质量及类型的丰富程度同时都提出了更高要求。在此基础上，双方将重点开拓和深耕本土市场，实行 “<strong>拓宽题材类型</strong>”、“<strong>拓展平台渠道</strong>” 以及 “<strong>丰富合作形式</strong>” 的战略计划，共同打造中国优秀原创动画作品。此次合作双方在优势互补、资源共享的基础上，实现多层面共赢。在坚持原创动画的特色和优势基础上，拓展资源、加强联盟。</p>]]></content>
    
    
    <categories>
      
      <category>合作</category>
      
    </categories>
    
    
    <tags>
      
      <tag>合作</tag>
      
    </tags>
    
  </entry>
  
  
  
  <entry>
    <title>孵化项目进展分享 —— 蔡采贝《银幕》入围渥太华国际动画节</title>
    <link href="/2022/07/18/%E4%B8%9C%E5%B8%83%E6%B4%B2%E5%AD%B5%E5%8C%96%E9%A1%B9%E7%9B%AE%E2%80%94%E8%94%A1%E9%87%87%E8%B4%9D%E3%80%8A%E9%93%B6%E5%B9%95%E3%80%8B%E5%85%A5%E5%9B%B4%E6%B8%A5%E5%A4%AA%E5%8D%8E%E5%9B%BD%E9%99%85%E5%8A%A8%E7%94%BB%E8%8A%82/"/>
    <url>/2022/07/18/%E4%B8%9C%E5%B8%83%E6%B4%B2%E5%AD%B5%E5%8C%96%E9%A1%B9%E7%9B%AE%E2%80%94%E8%94%A1%E9%87%87%E8%B4%9D%E3%80%8A%E9%93%B6%E5%B9%95%E3%80%8B%E5%85%A5%E5%9B%B4%E6%B8%A5%E5%A4%AA%E5%8D%8E%E5%9B%BD%E9%99%85%E5%8A%A8%E7%94%BB%E8%8A%82/</url>
    
    <content type="html"><![CDATA[<p>自 2020 年东布洲国际动画基地开启动画孵化项目以来，已有多个项目陆续完成孵化。本着助力动画创作“最初一公里”的初衷，我们不仅支持商业动画的创作与孵化，同时也更加关注原创独立动画的发展，希望中国的独立动画创作能走得更远。</p><h2 id="项目介绍"><a href="#项目介绍" class="headerlink" title="项目介绍"></a>项目介绍</h2><p><img src="http://img.heqing.co/20220718113706.png" alt="《银幕》海报"></p><p>本次跟大家分享的是2020年末入驻基地的独立动画项目《银幕》，它是由独立动画导演蔡采贝创作的。目前，根据组委会公布的最新消息，《银幕》已经入围了<strong>渥太华国际动画节（OIAF）</strong>的<strong>非叙事短片竞赛单元（Non-Narrative Short Film Competition）</strong>，祝贺蔡采贝导演！</p><p>渥太华国际动画节（Ottawa International Animation Festival）与昂西国际动画电影节、萨格勒布国际动画电影节、广岛国际动画电影节并称为世界四大动画电影节。渥太华动画节的特点是鼓励个性、富有思想与批判性的作品。今年的渥太华国际动画节（OIAF）将于 9 月 21 日至 25 日举行。</p><h2 id="作品截图欣赏"><a href="#作品截图欣赏" class="headerlink" title="作品截图欣赏"></a>作品截图欣赏</h2><blockquote><p>“踏入一个洞穴，视线借着火光起伏。左至右，上至下。</p></blockquote><p><img src="http://img.heqing.co/20220718113837.png" alt="《银幕》截图"></p><blockquote><p>你眼前的屏幕也是如此。它是一个无边界的通道，上演着驯化与渴望。”</p></blockquote><p><img src="http://img.heqing.co/20220718114014.png" alt="《银幕》截图"></p><p>在导演以往的艺术实践里，她常常关注影像中的触觉表现。通过触觉，人们可以理解空间。而这一部作品则在打破以往稳定的空间。不是将物放进取景框这个现有的空间中。相反，是物构建出了取景框里的空间。因此，影片中的边界不断游移，并调试着不同角度。</p><h2 id="作者介绍"><a href="#作者介绍" class="headerlink" title="作者介绍"></a>作者介绍</h2><center><img src="http://img.heqing.co/20220718114151.png" width="50%" height="50%" /></center><p>蔡采贝，1992 出生于广东深圳。她分别从江南大学和英国皇家艺术学院获得硕士学位。她痴迷于屏幕上的幻像并相信影像具有身体。她擅长用逐帧绘制的工作方式去捕获这些隐匿的身体，她制作陷阱的材料包括但不限于：指纹绒毛、反射鳞片、像素泪珠和一条阴晴不定的尾巴。她的片子总是在邀请观众一起去感知身体内部的冲突以及所处的不安环境。</p><h2 id="关于东布洲国际动画孵化基地"><a href="#关于东布洲国际动画孵化基地" class="headerlink" title="关于东布洲国际动画孵化基地"></a>关于东布洲国际动画孵化基地</h2><p>东布洲国际动画孵化创作基地的初衷是鼓励和扶持优秀的原创动画人，尤其年轻动画新锐，助力动画的“最初的一公里”。每年将挑选一批优质的项目进入东布洲孵化名单，目前已经持续第三年，还将持续进行。</p><p>孵化项目入驻东布洲国际动画孵化创作基地后，我们将组织业内动画创作、营销、平台等方面专家，针对孵化项目现有优势及问题提出评估报告，为孵化团队的创作提供参考，并整合各种专业资源，根据团队的需要在后续编剧、分镜、造型、场景、动画和音乐等各环节提供专业指导和评估。</p><p>此外，我们也将通过东布洲动画研究院举办的讲座和论坛等，帮助孵化团队创作人员提升自我，同时也通过不定期举办的动画人聚会，为动画人创造交流的环境。</p>]]></content>
    
    
    <categories>
      
      <category>孵化</category>
      
    </categories>
    
    
    <tags>
      
      <tag>孵化分享</tag>
      
    </tags>
    
  </entry>
  
  
  
  <entry>
    <title>2022 第四届东布洲国际动画周竞赛单元作品征集</title>
    <link href="/2022/06/01/2022recruit/"/>
    <url>/2022/06/01/2022recruit/</url>
    
    <content type="html"><![CDATA[<p>第四届 “东布洲国际动画周” 暨第十一届 “中国独立动画电影论坛” 将于 2022 年 10 月下旬在江苏海门临江新区举办。届时我们将邀请动画行业的专家学者、行业精英、知名导演、年轻创作者汇聚一堂，共同见证这个属于动画人自己的节日！</p><p>中国独立动画电影论坛（简称 CIAFF）是中国内地首个非盈利、由民间机构策划的动画电影艺术项目。2011 年由独立动画导演皮三首次发起。旨在鼓励艺术创作精神，聚集和扶持优质中国原创力量，推动中国动画的创作发展水平。2015 年起论坛实行策展人制，策展人负责一届论坛主题规划与活动安排。2019 年起，CIAFF 落地临江新区，与东布洲国际动画周（简称 TOPUIAW ）合并举办。</p><center><img src="http://img.heqing.co/20220713104256.png" width="50%" height="50%" /></center><p>竞赛单元是活动的重要组成部分。十一年来，秉承鼓励和扶持原创动画的精神，发掘和展现了一大批优秀的原创独立动画作品。截止 2021 年 12 月，我们共收到了来自<strong>海内外 50 多所高校</strong>的<strong>投稿作品 4800 多部</strong>，总计入围作品 418 部，评选出获奖作品 66 部。论坛将对入围作品及作者进行专访报道等宣传和推广，并有机会推荐参与国内外知名动画电影节，推荐参加展览和交流，与重要机构、企业进行合作。</p><p><img src="http://img.heqing.co/20220713104349.png" alt="2021 东布洲国际动画周论坛大奖 《Coffin》"></p><p>本次征集依然本着开放和多样性的原则，对题材、类型和形式不做任何的限制，欢迎一切有趣味、有想象力、有创造力，具有独立思考的动画作品。  </p><h2 id="作品征集时间"><a href="#作品征集时间" class="headerlink" title="作品征集时间"></a>作品征集时间</h2><p>2022 年 6 月 1 日 - 2022 年 8 月 31 日</p><h2 id="奖项设置"><a href="#奖项设置" class="headerlink" title="奖项设置"></a>奖项设置</h2><p>论坛大奖、论坛特别奖<br>实验动画奖<br>今敏奖<br>学生作品奖、评委特别推荐奖</p><h2 id="作品征集细则"><a href="#作品征集细则" class="headerlink" title="作品征集细则"></a>作品征集细则</h2><ul><li>不收取任何报名费用。</li><li>参赛作品需为逐帧动画，包括电脑绘图动画。</li><li>作品内容题材不限。</li><li>作品应完成于 2021 年 7 月之后。不接受过去曾参加过本竞赛的作品再次参赛。 </li><li>未获得版权许可的内容，剧本，音乐等不可用于所提交的作品。如无法获得许可，将失去参赛资格。有第三者发起侵权、索赔等诉讼时，东布洲国际动画周概不负责。</li><li>其他电影节已获奖作品仍然可以参赛，但需在报名表上列出所获奖项信息。</li><li>只要达到上述条件，同一参赛者可提交多部作品参赛。</li></ul><h2 id="作品投递所需资料"><a href="#作品投递所需资料" class="headerlink" title="作品投递所需资料"></a>作品投递所需资料</h2><h3 id="【报名表】"><a href="#【报名表】" class="headerlink" title="【报名表】"></a>【报名表】</h3><p>请参赛者通过官方渠道下载：请关注官方微信公众号，回复 “报名” 即可下载报名表。</p><h3 id="【导演简历、照片】"><a href="#【导演简历、照片】" class="headerlink" title="【导演简历、照片】"></a>【导演简历、照片】</h3><ul><li>简历格式可参见报名表 “附表 1”。</li><li>清晰的导演 &#x2F; 团队成员的生活照（5M 左右，JPEG&#x2F;PNG，300dpi）</li></ul><h3 id="【作品图片】"><a href="#【作品图片】" class="headerlink" title="【作品图片】"></a>【作品图片】</h3><ul><li>1 张海报、3 张作品剧照（5M 左右，JPEG&#x2F;PNG，300dpi）</li><li>照片文件需以人名或作品名命名。</li><li>这些照片与图片将被刊登于论坛官方平台、宣传单等广告物料或宣传册中。组委会可能会将收到的照片与图片剪辑使用，敬请谅解。</li></ul><h3 id="【影片】"><a href="#【影片】" class="headerlink" title="【影片】"></a>【影片】</h3><ul><li>影片格式可采用：MOV、AVI、MP4、或 WMV 。作品分辨率不得小于 720p ，并尽量采用低压缩或无损压缩方式。暂不接受 DCP 文件。</li><li>如果你的作品入围，需要在 10 月 10 日前向论坛组委会提供用于展映的高清格式：MOV、MPEG、MWV、MP4（H.264，分辨率为 1920 × 1080 及以上），暂不接受 DCP、35mm、16mm 胶片、HD-CAM 等格式。</li><li>有旁白或对白的影片请添加英文字幕。中文影片请添加中英文双语字幕。</li></ul><h2 id="作品投递方式"><a href="#作品投递方式" class="headerlink" title="作品投递方式"></a>作品投递方式</h2><h3 id="【-Email-投递】"><a href="#【-Email-投递】" class="headerlink" title="【 Email 投递】"></a>【 Email 投递】</h3><ul><li>一份报名表仅代表一部作品，请将【报名表】、【导演简历、照片】、【作品图片】和【影片】一起邮件提交至组委会指定邮箱。</li><li>报名邮件请以 “2022 第四届东布洲国际动画周竞赛单元 + 作品名 + 作者姓名” 为邮件主题。网盘地址下载、电子邮件超大附件皆可。</li><li>邮箱地址：<a href="mailto:&#115;&#117;&#98;&#x6d;&#105;&#115;&#x73;&#x69;&#x6f;&#110;&#x73;&#x40;&#x74;&#111;&#x70;&#117;&#105;&#97;&#x77;&#46;&#x63;&#x6f;&#109;">&#115;&#117;&#98;&#x6d;&#105;&#115;&#x73;&#x69;&#x6f;&#110;&#x73;&#x40;&#x74;&#111;&#x70;&#117;&#105;&#97;&#x77;&#46;&#x63;&#x6f;&#109;</a></li></ul><h3 id="【-Film-Freeway-在线投递】"><a href="#【-Film-Freeway-在线投递】" class="headerlink" title="【 Film Freeway 在线投递】"></a>【 Film Freeway 在线投递】</h3><p> <a href="https://filmfreeway.com/TOPUInternationalAnimationWeek">https://filmfreeway.com/TOPUInternationalAnimationWeek</a></p><h3 id="【邮寄快件】"><a href="#【邮寄快件】" class="headerlink" title="【邮寄快件】"></a>【邮寄快件】</h3><p>一份报名表仅代表一部作品，【报名表】、【导演简历、照片】、【作品图片】和【影片】一起刻盘邮寄至组委会指定地址。</p><ol><li>请在光盘上标注作者姓名、作品名称、联系电话。</li><li>请在快件上标注 “2022 第四届东布洲国际动画周竞赛单元”。</li><li>所有作品都有丢失的可能，论坛有权拒收任何到付邮费的邮件快递。</li><li>因报名所产生的邮费等所有费用均由参赛者承担。</li><li>邮寄作品按照当地邮戳时间为准。请在规定时间内投递，逾期将失去参加资格。</li></ol><h2 id="联系方式"><a href="#联系方式" class="headerlink" title="联系方式"></a>联系方式</h2><p>邮寄地址：江苏省南通市海门临江新区洞庭湖路 99 号东布洲国际动画孵化创作基地<br>收件人：东布洲国际动画周组委会<br>邮编：226100<br>联系电话：0086 138 1030 2830 或 0086 176 1083 2391</p><h2 id="报名表"><a href="#报名表" class="headerlink" title="报名表"></a>报名表</h2><p>请点击下载<a href="https://pan.baidu.com/share/init?surl=HNfhBOqIVXrpdAMEln18lw">报名表</a>，提取码 “ 7m2i ”</p>]]></content>
    
    
    <categories>
      
      <category>动画周</category>
      
    </categories>
    
    
    <tags>
      
      <tag>征集</tag>
      
    </tags>
    
  </entry>
  
  
  
  <entry>
    <title>孵化项目进展分享 —— 《崔文子学仙》入围瑞士萨维尼动画电影节</title>
    <link href="/2022/05/26/%E5%AD%B5%E5%8C%96%E9%A1%B9%E7%9B%AE%E8%BF%9B%E5%B1%95%E5%88%86%E4%BA%AB-%E2%80%94%E2%80%94-%E3%80%8A%E5%B4%94%E6%96%87%E5%AD%90%E5%AD%A6%E4%BB%99%E3%80%8B/"/>
    <url>/2022/05/26/%E5%AD%B5%E5%8C%96%E9%A1%B9%E7%9B%AE%E8%BF%9B%E5%B1%95%E5%88%86%E4%BA%AB-%E2%80%94%E2%80%94-%E3%80%8A%E5%B4%94%E6%96%87%E5%AD%90%E5%AD%A6%E4%BB%99%E3%80%8B/</url>
    
    <content type="html"><![CDATA[<p><img src="http://img.heqing.co/20220721205229.png"></p><p>自 2020 年东布洲国际动画基地开启动画孵化项目以来，已有多个项目陆续完成孵化。本着助力动画创作 “最初一公里” 的初衷，我们不仅支持商业动画的创作与孵化，同时也更加关注原创独立动画的发展，寄希望于中国的独立动画创作能走的更远。</p><p>本次介绍的《崔文子学仙》是 2021 年入驻基地的独立动画项目，动画以志怪小说《搜神记》里的一则故事为原型，探讨了人与自然能量场之间的关系。截止到目前的投递情况，《崔文子学仙》已经入围<strong>瑞士萨维尼动画电影节</strong> 。</p><p><img src="http://img.heqing.co/20220721205307.png"></p><blockquote><p>“曾经有一只美丽的生物，在我梦里出现过。但是之后我再也没有见到过它。” </p></blockquote><p>自然界中，能量不但可以从一个物体转移到另一个物体，多种能量之间还可以相互转化；这种特殊的循环就会产生能量场。物与物之间的转化是某种不变的能量的体现。自然能量以大鸟的姿态示人又离去，给人留下似梦非梦的物哀之情。</p><h1 id="创作人介绍"><a href="#创作人介绍" class="headerlink" title="创作人介绍"></a>创作人介绍</h1><p><strong>王家琪</strong><br>本科毕业于中央美术学院，研究生毕业于英国皇家艺术学院。她的动画作品善于通过符号隐喻的方式讲述真实的故事，通过版刻的媒介将粗糙的画面质感与细腻的独白结合。《2.3 x 2.6 x 3.2》曾参加伦敦国际动画节、渥太华国际动画节和爱丁堡国际电影节，还赢得了 Monstra 国际动画节的最佳学生影片。《龙头树》获得第三届东布洲国际动画周 “实验动画奖”。<br>网站: <a href="http://www.jackiestudio.com/">www.jackiestudio.com</a><br>邮箱：<a href="mailto:&#106;&#x61;&#x63;&#x6b;&#105;&#101;&#x77;&#x6f;&#114;&#x6b;&#x40;&#x6f;&#x75;&#116;&#x6c;&#x6f;&#x6f;&#107;&#46;&#99;&#111;&#x6d;">&#106;&#x61;&#x63;&#x6b;&#105;&#101;&#x77;&#x6f;&#114;&#x6b;&#x40;&#x6f;&#x75;&#116;&#x6c;&#x6f;&#x6f;&#107;&#46;&#99;&#111;&#x6d;</a></p><p><img src="http://img.heqing.co/20220721205514.png"><br>《崔文子学仙》的国画风背景，由岳一川绘制。岳一川本科和硕士均毕业于中央美术学院，其作品入选联合国非物质文化遗产、美国集邮集团、欧洲集邮集团联合出品 “庆祝建国 70 周年主题邮票” 出版并发行。目前于首都师范大学美术学院攻读博士学位。</p><p><img src="http://img.heqing.co/20220721205553.png"></p><h1 id="角色设计"><a href="#角色设计" class="headerlink" title="角色设计"></a>角色设计</h1><p><img src="http://img.heqing.co/20220721205728.png"><br><img src="http://img.heqing.co/20220721205739.png"><br><img src="http://img.heqing.co/20220721205752.png"></p><h1 id="影片截图"><a href="#影片截图" class="headerlink" title="影片截图"></a>影片截图</h1><p><img src="http://img.heqing.co/20220721205814.png"><br><img src="http://img.heqing.co/20220721205822.png"><br><img src="http://img.heqing.co/20220721205833.png"><br><img src="http://img.heqing.co/20220721205846.png"></p>]]></content>
    
    
    <categories>
      
      <category>孵化</category>
      
    </categories>
    
    
    <tags>
      
      <tag>孵化分享</tag>
      
    </tags>
    
  </entry>
  
  
  
  <entry>
    <title>孵化项目进展分享 ——《元气小队》广播剧在喜马拉雅平台推出</title>
    <link href="/2022/05/09/%E5%AD%B5%E5%8C%96%E9%A1%B9%E7%9B%AE%E8%BF%9B%E5%B1%95%E5%88%86%E4%BA%AB-%E2%80%94%E2%80%94%E3%80%8A%E5%85%83%E6%B0%94%E5%B0%8F%E9%98%9F%E3%80%8B/"/>
    <url>/2022/05/09/%E5%AD%B5%E5%8C%96%E9%A1%B9%E7%9B%AE%E8%BF%9B%E5%B1%95%E5%88%86%E4%BA%AB-%E2%80%94%E2%80%94%E3%80%8A%E5%85%83%E6%B0%94%E5%B0%8F%E9%98%9F%E3%80%8B/</url>
    
    <content type="html"><![CDATA[<p><img src="http://img.heqing.co/20220721204049.png"></p><p>2020 年 6 月，东布洲国际动画孵化创作基地迎来第一批项目的入驻团队，东布洲原创优质动画的孵化之旅从那时起正式启程。截止至 2022 年，我们欣喜的观察到，一些项目已经结束了孵化期进入行业内，与平台合作并推向市场，增加了原创性作品市场的力量。</p><p>本次将为大家介绍的是针对 3 - 6 岁小朋友、绘本风的冒险科普类动画亲子剧集项目《元气小队》，该项目由 “核子章鱼工作室” 开发创作，也是第一批入住孵化创作基地的项目之一。目前《元气小队》正在努力拓展其 IP 的内容范畴，不仅在 “喜马拉雅儿童版” 以广播剧的形式推出了 200 集音频，并且之后在其主站上线的时候还会推出动态绘本和短视频。</p><p><img src="http://img.heqing.co/20220721204317.png"></p><p>《元气小队》团队创作的起因是源于 2020 年后世界对病毒和公共卫生的关注上升到前所未有的程度，在这种背景下创作团队决定开启关于微观世界的题材，并把着眼点放在了人体内部。该项目以人体为故事的舞台，融合了探索、冒险、拯救、守卫等元素。讲述了微观世界几个成员组成的守护小队的故事，他们组成守卫人体的元气小队，探索人体内各种现象，解决人体所遇到的各种危机，保持人体世界的和平。</p><p><img src="http://img.heqing.co/20220721204527.png"></p><p>《元气小队》每集故事都是一次单独的冒险，成员们会发挥自己的特殊本领，带领小观众领略微观世界的秘密，了解自己身体的知识，并养成良好的生活习惯。故事中包含的知识点、新奇的世界观、时尚感的造型和画面，也能让父母感受观看的乐趣。</p><p><img src="http://img.heqing.co/20220721204607.png"></p><p><img src="http://img.heqing.co/20220721204635.png"></p><p><img src="http://img.heqing.co/20220721204721.png"></p>]]></content>
    
    
    <categories>
      
      <category>孵化</category>
      
    </categories>
    
    
    <tags>
      
      <tag>孵化分享</tag>
      
    </tags>
    
  </entry>
  
  
  
  <entry>
    <title>2022 年度东布洲动画孵化项目报名通道即将截止</title>
    <link href="/2022/01/08/%E3%80%90%E5%80%92%E8%AE%A1%E6%97%B6%E4%B8%80%E5%91%A8%E3%80%912022-%E5%B9%B4%E5%BA%A6%E4%B8%9C%E5%B8%83%E6%B4%B2%E5%8A%A8%E7%94%BB%E5%AD%B5%E5%8C%96%E9%A1%B9%E7%9B%AE%E6%8A%A5%E5%90%8D%E9%80%9A%E9%81%93%E5%8D%B3%E5%B0%86%E6%88%AA%E6%AD%A2/"/>
    <url>/2022/01/08/%E3%80%90%E5%80%92%E8%AE%A1%E6%97%B6%E4%B8%80%E5%91%A8%E3%80%912022-%E5%B9%B4%E5%BA%A6%E4%B8%9C%E5%B8%83%E6%B4%B2%E5%8A%A8%E7%94%BB%E5%AD%B5%E5%8C%96%E9%A1%B9%E7%9B%AE%E6%8A%A5%E5%90%8D%E9%80%9A%E9%81%93%E5%8D%B3%E5%B0%86%E6%88%AA%E6%AD%A2/</url>
    
    <content type="html"><![CDATA[<p>东布洲国际动画孵化创作基地（以下简称基地），位于江苏海门临江新区，与上海隔江相望，环境优美，气候宜人，非常适合驻地创作，基于国内动画行业蓬勃发展的产业契机、基地具备的行业优势资源和政府营造的舒适环境，2020 年起，基地正式开启原创动画项目孵化申报通道，招募处于前期创作研发阶段的动画项目入驻基地。截止目前，已有 20 个项目在基地开始孵化，其中首批 7 个孵化项目已阶段性完成孵化工作。</p><p>2021 年 12 月 4 日，基地正式开启 2022 年动画孵化项目的申报通道，报名截止 2022 年 1 月 15 日。基地的初衷是鼓励和扶持优秀的原创动画人，尤其年轻动画新锐，助力动画的 “最初的一公里”。2022 年，基地将在总结成功经验基础上，进一步优化孵化机制和模式，投入更多资源和力量，尤其是加强对于高校优秀毕业生项目的孵化和支持。希望更多关注原创动画、热爱原创动画的人，关注和支持基地的发展，也再次诚挚邀请各位有志于创作的动画人加入我们。只要您有好的想法或创意，哪怕稚嫩，只要鲜活有力，欢迎踊跃报名，期待与您在东布洲相聚。</p><h1 id="东布洲国际动画孵化创作基地"><a href="#东布洲国际动画孵化创作基地" class="headerlink" title="东布洲国际动画孵化创作基地"></a>东布洲国际动画孵化创作基地</h1><h2 id="项目招募简则"><a href="#项目招募简则" class="headerlink" title="项目招募简则"></a>项目招募简则</h2><p>东布洲国际动画孵化创作基地（以下简称 “基地”），位于江苏海门临江新区，与上海隔江相望，媲美欧美小镇，营商氛围上佳，环境优美，气候宜人。2022 年，这里将开启新一期前期创作阶段的动画原创项目招募，欢迎有志于创作的动画人加入。</p><p>基地依托动画行业各个门类的领军人物，举办每年一届的 “东布洲国际动画周” 发现优秀作品和人才，举办每年一届的 “中国独立动画电影论坛” 搭建行业交流集聚的平台，同时基地下辖的 “动画研究院” 定期会举办专业学术活动，整合前期孵化资源，并在孵化完成后组织创投路演等活动推进项目的进一步开发。</p><p>为了更好的帮助国内外的动画人、原创作品，甄选优秀创意、发掘优秀团队，基地将投入资源和资金，与他们共同完善作品的 “最初一公里”，也即，把一个点子或想法逐步孵化成可以进入成熟开发阶段的项目。</p><p>我们诚挚地邀请各位动画人、动画导演、动画公司、工作室等前期孵化团队共同加入。</p><h2 id="基地投入资源"><a href="#基地投入资源" class="headerlink" title="基地投入资源"></a>基地投入资源</h2><h3 id="创作"><a href="#创作" class="headerlink" title="创作"></a>创作</h3><p>整合国内最优秀的创作人才予以指导，提升或补足项目创作上的短板。</p><h3 id="资金"><a href="#资金" class="headerlink" title="资金"></a>资金</h3><p>提供前期孵化资金，合理化投入完成前期动画研发。</p><h3 id="制片"><a href="#制片" class="headerlink" title="制片"></a>制片</h3><p>完善的前期孵化制片管理机制，协作行业资源完成项目孵化流程。</p><h3 id="驻地"><a href="#驻地" class="headerlink" title="驻地"></a>驻地</h3><p>提供集约化创作服务平台及舒适的工作环境，确保团队专注创作。</p><h3 id="出口"><a href="#出口" class="headerlink" title="出口"></a>出口</h3><p>孵化后协助团队进入中后期的开发，提供融资和内容的出口机制。</p><h2 id="项目入围要求"><a href="#项目入围要求" class="headerlink" title="项目入围要求"></a>项目入围要求</h2><h3 id="项目描述"><a href="#项目描述" class="headerlink" title="项目描述"></a>项目描述</h3><p>需提供 PPT 格式的项目提案，包括以下内容：</p><ul><li><p>简明的项目核心。</p></li><li><p>清晰的故事梗概。</p></li><li><p>独特的创意点。（这个项目和别的有何不同）</p></li><li><p>角色与场景的视觉设定。（不求完整但能看出大致风格）</p></li><li><p>主创介绍。（简历以及自我能力分析）</p></li></ul><h3 id="持续热情"><a href="#持续热情" class="headerlink" title="持续热情"></a>持续热情</h3><p>团队或主创有持续创作的能力及热情，不会出现半途而废、知难而退。</p><h3 id="驻地创作"><a href="#驻地创作" class="headerlink" title="驻地创作"></a>驻地创作</h3><p>团队需要有 2-6 个月的时间进行驻地创作，具体时间根据项目情况评估。</p><h3 id="孵化合作"><a href="#孵化合作" class="headerlink" title="孵化合作"></a>孵化合作</h3><p>与基地签订孵化协议，共同协商其中的制片管理、版权合作等内容。</p><h2 id="项目评估机制"><a href="#项目评估机制" class="headerlink" title="项目评估机制"></a>项目评估机制</h2><p>由项目决策委员会集体投票决策。<br>决策委员会将以该入围项目能否在东布洲国际动画孵化创作基地孵化后达成以下标准为考核依据。按类型：</p><ul><li><p>电影项目: 以 “专业电影公司投资” 为项目孵化完成的评价标准；</p></li><li><p>剧集项目: 以 “视频网站或电视台预购或参投” 为项目孵化完成的评价标准；</p></li><li><p>短片项目: 以 “达成各大动画节或电影节的选片要求” 为项目孵化完成的评价标准。</p></li></ul><p>每月初选、评估、审核完成，通过委员会投票的项目，将逐一洽谈孵化细节。</p><h2 id="东布洲孵化提案评审标准"><a href="#东布洲孵化提案评审标准" class="headerlink" title="东布洲孵化提案评审标准"></a>东布洲孵化提案评审标准</h2><p><img src="http://img.heqing.co/20220721203745.png" alt="东布洲孵化提案评审标准"></p><h2 id="申报开始日期"><a href="#申报开始日期" class="headerlink" title="申报开始日期"></a>申报开始日期</h2><p>2021 年 12 月 4 日</p><h2 id="申报截止日期"><a href="#申报截止日期" class="headerlink" title="申报截止日期"></a>申报截止日期</h2><p>2022 年 1 月 15 日</p><h2 id="项目申报窗口"><a href="#项目申报窗口" class="headerlink" title="项目申报窗口"></a>项目申报窗口</h2><p>邮箱：<a href="mailto:&#99;&#x69;&#x61;&#102;&#102;&#x40;&#113;&#x71;&#46;&#99;&#x6f;&#x6d;">&#99;&#x69;&#x61;&#102;&#102;&#x40;&#113;&#x71;&#46;&#99;&#x6f;&#x6d;</a><br>微信：sisolon<br>咨询电话：13810302830<br>联系人：司先生</p>]]></content>
    
    
    <categories>
      
      <category>孵化</category>
      
    </categories>
    
    
    <tags>
      
      <tag>孵化征集</tag>
      
    </tags>
    
  </entry>
  
  
  
  
</search>
